Metadata-Version: 1.0
Name: reactions
Version: 0.0.1
Summary: ('Python package to specify, simulate, and optimize over', 'chemical reactions')
Home-page: https://bitbucket.org/ankur-gupta/reactions
Author: Ankur Gupta
Author-email: ankur.gupta.phd@gmail.com
License: UNKNOWN
Platform: UNKNOWN
